perfflow/__about__.py
perfflow/__init__.py
perfflow-0.0.1.dist-info/METADATA
perfflow-0.0.1.dist-info/WHEEL
perfflow-0.0.1.dist-info/licenses/LICENSE.txt
perfflow-0.0.1.dist-info/RECORD
